aioja/__init__.py
aioja/compiler.py
aioja/environment.py
aioja/loaders.py
aioja/utils.py
aioja/bccache/__init__.py
aioja/bccache/aiocache.py
aioja/bccache/aioredis.py
tests/__init__.py
tests/conftest.py
tests/test_aiocache.py
tests/test_aioja.py
tests/test_aioredis.py
tests/test_loaders.py
tests/test_utils.py
aioja-0.0.4.dist-info/LICENSE
aioja-0.0.4.dist-info/METADATA
aioja-0.0.4.dist-info/WHEEL
aioja-0.0.4.dist-info/top_level.txt
aioja-0.0.4.dist-info/RECORD
