Metadata-Version: 2.1
Name: aioja
Version: 0.0.4
Summary: Async version of Jinja2 environment
Home-page: https://github.com/dldevinc/aioja
Author: Mihail Mishakin
Author-email: x896321475@gmail.com
Maintainer: Mihail Mishakin
Maintainer-email: x896321475@gmail.com
License: BSD license
Platform: OS Independent
Classifier: Intended Audience :: Developers
Classifier: Development Status :: 3 - Alpha
Classifier: License :: OSI Approved :: BSD License
Classifier: Operating System :: OS Independent
Classifier: Programming Language :: Python
Classifier: Programming Language :: Python :: 3
Classifier: Programming Language :: Python :: 3 :: Only
Classifier: Programming Language :: Python :: 3.6
Classifier: Programming Language :: Python :: 3.7
Classifier: Programming Language :: Python :: 3.8
Classifier: Topic :: Software Development :: Libraries :: Python Modules
Requires-Python: >=3.6
Requires-Dist: jinja2
Requires-Dist: aiofiles
Provides-Extra: aiocache
Requires-Dist: aiocache ; extra == 'aiocache'
Provides-Extra: aioredis
Requires-Dist: aioredis ; extra == 'aioredis'
